Metricus/__init__.py
Metricus/_formulas/__init__.py
Metricus/_formulas/acceleration_formulas.py
Metricus/_formulas/area_formulas.py
Metricus/_formulas/electricity_formulas.py
Metricus/_formulas/energy_formulas.py
Metricus/_formulas/force_formulas.py
Metricus/_formulas/length_formulas.py
Metricus/_formulas/mass_formulas.py
Metricus/_formulas/pressure_formulas.py
Metricus/_formulas/speed_formulas.py
Metricus/_formulas/temperature_formulas.py
Metricus/_formulas/time_formulas.py
Metricus/_formulas/volume_formulas.py
Metricus/_formulas/complex_formulas/__init__.py
Metricus/_formulas/complex_formulas/density_calculator.py
Metricus/_formulas/complex_formulas/displacement_calculator.py
Metricus/_formulas/complex_formulas/force_calculator.py
Metricus/_formulas/complex_formulas/pressure_calculator.py
Metricus/formulas/__init__.py
Metricus/formulas/acceleration_formulas.py
Metricus/formulas/area_formulas.py
Metricus/formulas/electricity_formulas.py
Metricus/formulas/energy_formulas.py
Metricus/formulas/force_formulas.py
Metricus/formulas/length_formulas.py
Metricus/formulas/mass_formulas.py
Metricus/formulas/pressure_formulas.py
Metricus/formulas/speed_formulas.py
Metricus/formulas/temperature_formulas.py
Metricus/formulas/time_formulas.py
Metricus/formulas/utilities.py
Metricus/formulas/volume_formulas.py
Metricus/formulas/complex_formulas/__init__.py
Metricus/formulas/complex_formulas/density_calculator.py
Metricus/formulas/complex_formulas/displacement_calculator.py
Metricus/formulas/complex_formulas/force_calculator.py
Metricus/formulas/complex_formulas/pressure_calculator.py
Metricus/gui/__init__.py
Metricus/gui/user_interface.py
Metricus/operations/__init__.py
Metricus/operations/acceleration.py
Metricus/operations/area.py
Metricus/operations/electricity.py
Metricus/operations/energy.py
Metricus/operations/force.py
Metricus/operations/length.py
Metricus/operations/mass.py
Metricus/operations/pressure.py
Metricus/operations/speed.py
Metricus/operations/temperature.py
metricus-1.0.5.dist-info/LICENSE
metricus-1.0.5.dist-info/METADATA
metricus-1.0.5.dist-info/WHEEL
metricus-1.0.5.dist-info/top_level.txt
metricus-1.0.5.dist-info/RECORD
